disstans/__init__.py
disstans/config.py
disstans/earthquakes.py
disstans/models.py
disstans/network.py
disstans/processing.py
disstans/solvers.py
disstans/station.py
disstans/timeseries.py
disstans/tools.py
disstans-2.2.dist-info/LICENSE
disstans-2.2.dist-info/METADATA
disstans-2.2.dist-info/WHEEL
disstans-2.2.dist-info/top_level.txt
disstans-2.2.dist-info/RECORD
