Metadata-Version: 2.1
Name: disstans
Version: 2.2
Summary: DISSTANS
Author-email: Tobias Köhne <47008700+tobiscode@users.noreply.github.com>
License: GNU GENERAL PUBLIC LICENSE
Project-URL: Repository, https://github.com/tobiscode/disstans
Project-URL: Documentation, https://tobiscode.github.io/disstans/
Project-URL: Bug Tracker, https://github.com/tobiscode/disstans/issues
Classifier: Intended Audience :: Science/Research
Classifier: Topic :: Scientific/Engineering
Classifier: License :: OSI Approved :: GNU General Public License v3 (GPLv3)
Classifier: Programming Language :: Python :: 3
Requires-Python: >=3.12
License-File: LICENSE
Requires-Dist: numpy >=1.26
Requires-Dist: scipy >=1.11
Requires-Dist: scikit-learn >=1.3
Requires-Dist: matplotlib >=3.8
Requires-Dist: cartopy >=0.22
Requires-Dist: pandas >=2.1
Requires-Dist: tqdm
Requires-Dist: cvxpy >=1.3
Requires-Dist: cmcrameri
Requires-Dist: owslib
Requires-Dist: sqlalchemy
Provides-Extra: okada
Requires-Dist: okada-wrapper >=24.6.15 ; extra == 'okada'
